xiaomi_flashable_firmware_creator/__init__.py
xiaomi_flashable_firmware_creator/__main__.py
xiaomi_flashable_firmware_creator/binaries/update-binary
xiaomi_flashable_firmware_creator/extractors/__init__.py
xiaomi_flashable_firmware_creator/extractors/handlers/base_handler.py
xiaomi_flashable_firmware_creator/extractors/handlers/payload_zip.py
xiaomi_flashable_firmware_creator/extractors/handlers/standard_zip.py
xiaomi_flashable_firmware_creator/extractors/ota_payload_extractor/.git
xiaomi_flashable_firmware_creator/extractors/ota_payload_extractor/.gitignore
xiaomi_flashable_firmware_creator/extractors/ota_payload_extractor/LICENSE
xiaomi_flashable_firmware_creator/extractors/ota_payload_extractor/README.md
xiaomi_flashable_firmware_creator/extractors/ota_payload_extractor/extract_android_ota_payload.py
xiaomi_flashable_firmware_creator/extractors/ota_payload_extractor/requirements.txt
xiaomi_flashable_firmware_creator/extractors/ota_payload_extractor/update_metadata_pb2.py
xiaomi_flashable_firmware_creator/extractors/zip_extractor.py
xiaomi_flashable_firmware_creator/firmware_creator.py
xiaomi_flashable_firmware_creator/helpers/__init__.py
xiaomi_flashable_firmware_creator/helpers/misc.py
xiaomi_flashable_firmware_creator/helpers/mock_zip.py
xiaomi_flashable_firmware_creator/templates/partition_flashing
xiaomi_flashable_firmware_creator/templates/recovery_ab_update-binary
xiaomi_flashable_firmware_creator/templates/recovery_ab_updater_script
xiaomi_flashable_firmware_creator/templates/recovery_updater_script
xiaomi_flashable_firmware_creator/tests/__init__.py
xiaomi_flashable_firmware_creator/tests/files/mtk/mocked_miui_BEGONIAGlobal_V11.0.6.0.PGGMIXM_41b14febb2_9.0.zip
xiaomi_flashable_firmware_creator/tests/files/mtk/mocked_miui_BEGONIAGlobal_V12.0.3.0.QGGMIXM_4bd96ae3c3_10.0.zip
xiaomi_flashable_firmware_creator/tests/files/mtk/mocked_miui_HM6Global_V10.3.6.0.OCGMIXM_85f41684de_8.1.zip
xiaomi_flashable_firmware_creator-2.3.0.dist-info/licenses/LICENSE
xiaomi_flashable_firmware_creator-2.3.0.dist-info/WHEEL
xiaomi_flashable_firmware_creator-2.3.0.dist-info/entry_points.txt
xiaomi_flashable_firmware_creator-2.3.0.dist-info/METADATA
xiaomi_flashable_firmware_creator-2.3.0.dist-info/RECORD
