Metadata-Version: 2.4
Name: xiaomi-flashable-firmware-creator
Version: 2.3.0
Summary: Create flashable firmware zip from MIUI and HyperOS Recovery ROMs!
Keywords: xiaomi,firmware,android
Author: yshalsager
Author-email: yshalsager <contact@yshalsager.com>
License-File: LICENSE
Requires-Dist: remotezip>=0.12.3
Requires-Dist: protobuf>=6.32.1,<6.33.0
Requires-Python: >=3.13
Project-URL: homepage, https://xmfirmwareupdater.com/projects/xiaomi-flashable-firmware-creator/
Project-URL: repository, https://github.com/XiaomiFirmwareUpdater/xiaomi-flashable-firmware-creator/
